bats_tda.libs/libgomp-a34b3233.so.1.0.0
bats/linalg_f2.cpython-39-x86_64-linux-gnu.so
bats/topology.cpython-39-x86_64-linux-gnu.so
bats/linalg_auto.cpython-39-x86_64-linux-gnu.so
bats/__init__.py
bats/linalg.cpython-39-x86_64-linux-gnu.so
bats/linalg_f3.cpython-39-x86_64-linux-gnu.so
bats/_version.py
bats/dense.cpython-39-x86_64-linux-gnu.so
bats/visualization/__init__.py
bats/visualization/plotly.py
bats/visualization/visualization.py
bats_tda-0.2.0.dist-info/top_level.txt
bats_tda-0.2.0.dist-info/WHEEL
bats_tda-0.2.0.dist-info/RECORD
bats_tda-0.2.0.dist-info/LICENSE
bats_tda-0.2.0.dist-info/METADATA
