Metadata-Version: 2.1
Name: bats-tda
Version: 0.2.0
Summary: Python bindings for the Basic Applied Topology Subprograms
Home-page: https://github.com/CompTop/BATS.py
Author: Brad Nelson
Author-email: bradnelson@uchicago.edu
License: UNKNOWN
Project-URL: Bug Tracker, https://github.com/CompTop/BATS.py/issues
Keywords: algebraic topology,topological data analysis,persistent homology,zigzag homology
Platform: UNKNOWN
Classifier: Development Status :: 3 - Alpha
Classifier: Intended Audience :: Developers
Classifier: Intended Audience :: Education
Classifier: Intended Audience :: Science/Research
Classifier: Topic :: Software Development :: Libraries :: Python Modules
Classifier: Topic :: Utilities
Classifier: Topic :: Scientific/Engineering :: Mathematics
Classifier: Programming Language :: C++
Classifier: Programming Language :: Python :: 3
Classifier: Programming Language :: Python :: 3.6
Classifier: Programming Language :: Python :: 3.7
Classifier: Programming Language :: Python :: 3.8
Classifier: Programming Language :: Python :: 3.9
Classifier: Programming Language :: Python :: 3.10
Classifier: License :: OSI Approved :: MIT License
Classifier: Operating System :: POSIX :: Linux
Classifier: Operating System :: MacOS :: MacOS X
Requires-Python: >=3.6
License-File: LICENSE
